zxart/__init__.py
zxart/__main__.py
zxart/client.py
zxart/common.py
zxart/image.py
zxart/models.py
zxart/tune.py
zxart-0.3.5.dist-info/METADATA
zxart-0.3.5.dist-info/WHEEL
zxart-0.3.5.dist-info/licenses/LICENSE
zxart-0.3.5.dist-info/RECORD
